HtmlPyrser/__init__.py
HtmlPyrser/parser.py
HtmlPyrser/types.py
HtmlPyrser-0.1.1.dist-info/LICENSE
HtmlPyrser-0.1.1.dist-info/METADATA
HtmlPyrser-0.1.1.dist-info/WHEEL
HtmlPyrser-0.1.1.dist-info/top_level.txt
HtmlPyrser-0.1.1.dist-info/RECORD
