Metadata-Version: 2.1
Name: HtmlPyrser
Version: 0.1.1
Summary: A simple, fast and pure-python HTML parser
Home-page: https://github.com/witer33/Python-HTML-Parser
Author: Witer33
Author-email: dev@witer33.com
License: UNKNOWN
Download-URL: https://github.com/witer33/Python-html-parser/archive/v0.1.1.tar.gz
Platform: UNKNOWN
Classifier: Programming Language :: Python :: 3
Classifier: Operating System :: OS Independent
Classifier: License :: OSI Approved :: GNU Lesser General Public License v3 (LGPLv3)
Requires-Python: >=3.5
